fabricdocker/__init__.py
fabricdocker/fabricdocker.py
fabricdocker/compose/__init__.py
fabricdocker/docker/__init__.py
fabricdocker-0.1.3.dist-info/AUTHORS.rst
fabricdocker-0.1.3.dist-info/LICENSE
fabricdocker-0.1.3.dist-info/METADATA
fabricdocker-0.1.3.dist-info/WHEEL
fabricdocker-0.1.3.dist-info/top_level.txt
fabricdocker-0.1.3.dist-info/RECORD
