Metadata-Version: 2.1
Name: fabricdocker
Version: 0.1.3
Summary: Modern Fabric tools for docker
Home-page: https://github.com/gdelfresno/fabricdocker
Author: Guillermo del Fresno
Author-email: gdelfresno@gmail.com
License: MIT license
Keywords: fabricdocker
Platform: UNKNOWN
Classifier: Development Status :: 2 - Pre-Alpha
Classifier: Intended Audience :: Developers
Classifier: License :: OSI Approved :: MIT License
Classifier: Natural Language :: English
Classifier: Programming Language :: Python :: 2
Classifier: Programming Language :: Python :: 2.7
Classifier: Programming Language :: Python :: 3
Classifier: Programming Language :: Python :: 3.4
Classifier: Programming Language :: Python :: 3.5
Classifier: Programming Language :: Python :: 3.6
Classifier: Programming Language :: Python :: 3.7
Requires-Dist: fabric (==2.6.0)
Requires-Dist: invoke (==1.5.0)
